brliant_calc/__init__.py
brliant_calc/__main__.py
brliant_calc/advanced_ops.py
brliant_calc/alias_manager.py
brliant_calc/basic_ops.py
brliant_calc/complex_ops.py
brliant_calc/convert_currency.py
brliant_calc/dimensional_analysis.py
brliant_calc/matrix_ops.py
brliant_calc/physics_formulas.py
brliant_calc/plotting.py
brliant_calc/precision_ops.py
brliant_calc/symbolic_ops.py
brliant_calc/units.py
brliant_calc/vectors.py
brliant_calc-3.0.1.dist-info/licenses/LICENSE
brliant_calc-3.0.1.dist-info/METADATA
brliant_calc-3.0.1.dist-info/WHEEL
brliant_calc-3.0.1.dist-info/entry_points.txt
brliant_calc-3.0.1.dist-info/top_level.txt
brliant_calc-3.0.1.dist-info/RECORD
