Metadata-Version: 2.4
Name: brliant_calc
Version: 3.0.1
Summary: A advanced calculator for complicated mathematics.
Author-email: Aarav Maloo <aaravmaloo06@email.com>
License: MIT
Project-URL: Homepage, https://github.com/aaravmaloo/brliant_calc
Project-URL: Repository, https://github.com/aaravmaloo/brliant_calc
Project-URL: Bug Tracker, https://github.com/aaravmaloo/brliant_calc/issues
Keywords: calculator,scientific,mathematics,cli,symbolic,matrix,physics
Classifier: Development Status :: 4 - Beta
Classifier: Intended Audience :: Developers
Classifier: Intended Audience :: Science/Research
Classifier: Intended Audience :: Education
Classifier: License :: OSI Approved :: MIT License
Classifier: Operating System :: OS Independent
Classifier: Programming Language :: Python :: 3
Classifier: Programming Language :: Python :: 3.9
Classifier: Programming Language :: Python :: 3.10
Classifier: Programming Language :: Python :: 3.11
Classifier: Programming Language :: Python :: 3.12
Classifier: Topic :: Scientific/Engineering :: Mathematics
Classifier: Topic :: Scientific/Engineering :: Physics
Classifier: Topic :: Utilities
Requires-Python: >=3.9
License-File: LICENSE
Requires-Dist: numpy>=1.20.0
Requires-Dist: sympy>=1.10.0
Requires-Dist: matplotlib>=3.3.0
Requires-Dist: pint>=0.18.0
Requires-Dist: currency-converter>=0.5.0
Dynamic: license-file
